pytds/__init__.py
pytds/collate.py
pytds/extensions.py
pytds/lcid.py
pytds/login.py
pytds/smp.py
pytds/sspi.py
pytds/tds.py
pytds/tds_base.py
pytds/tds_types.py
pytds/tls.py
pytds/tz.py
python_tds_readonly_fork-1.11.1.dist-info/LICENSE.txt
python_tds_readonly_fork-1.11.1.dist-info/METADATA
python_tds_readonly_fork-1.11.1.dist-info/WHEEL
python_tds_readonly_fork-1.11.1.dist-info/top_level.txt
python_tds_readonly_fork-1.11.1.dist-info/zip-safe
python_tds_readonly_fork-1.11.1.dist-info/RECORD
