Metadata-Version: 2.1
Name: python-tds-readonly-fork
Version: 1.11.1
Summary: Python DBAPI driver for MSSQL using pure Python TDS (Tabular Data Stream) protocol implementation
Home-page: https://github.com/denisenkom/pytds
Author: Mikhail Denisenko
Author-email: denisenkom@gmail.com
License: MIT
Classifier: Development Status :: 4 - Beta
Classifier: Programming Language :: Python
Classifier: Programming Language :: Python :: 2.7
Classifier: Programming Language :: Python :: 3.3
Classifier: Programming Language :: Python :: 3.4
Classifier: Programming Language :: Python :: 3.5
License-File: LICENSE.txt
Requires-Dist: six (>=1.4.1)
